{"tasks":[{"id":"7833e80f-cbdf-4b63-b312-bdd270ee8cd8","title":"Task 1 Updated again","description":"This is Task 1 updated again","completed_at":null,"created_at":"2023-11-28T11:49:59-03:00","updated_at":"2023-11-28T12:03:12-03:00"},{"id":"9e55f464-1d94-4821-bfff-08378de6c16d","title":"Task 02","description":"Descrição da Task 02","completed_at":null,"created_at":"2023-11-28T11:49:59-03:00","updated_at":"2023-11-28T11:49:59-03:00"},{"id":"cb578f09-4e05-4e56-a537-21385f8082eb","title":"Task 03","description":"Descrição da Task 03","completed_at":null,"created_at":"2023-11-28T11:49:59-03:00","updated_at":"2023-11-28T11:49:59-03:00"},{"id":"19d757f6-0355-4fc2-afd6-5c3cf16816f7","title":"Task 04","description":"Descrição da Task 04","completed_at":null,"created_at":"2023-11-28T11:49:59-03:00","updated_at":"2023-11-28T11:49:59-03:00"},{"id":"754d0fbd-0878-4974-93b3-c48c71ace8c7","title":"Task 05","description":"Descrição da Task 05","completed_at":null,"created_at":"2023-11-28T11:49:59-03:00","updated_at":"2023-11-28T11:49:59-03:00"},{"id":"f7968feb-865a-4c18-bdc3-ea64bc1bd241","title":"Task 06","description":"Descrição da Task 06","completed_at":null,"created_at":"2023-11-28T11:49:59-03:00","updated_at":"2023-11-28T11:49:59-03:00"},{"id":"f85aaf60-90a1-4d86-a7d7-522308aae125","title":"Task 07","description":"Descrição da Task 07","completed_at":null,"created_at":"2023-11-28T11:49:59-03:00","updated_at":"2023-11-28T11:49:59-03:00"},{"id":"1bc9cc14-82b5-429a-88b9-eb344ee1b09d","title":"Task 08","description":"Descrição da Task 08","completed_at":null,"created_at":"2023-11-28T11:49:59-03:00","updated_at":"2023-11-28T11:49:59-03:00"},{"id":"059cd1cd-279e-4ecc-8ac0-6bcd56432162","title":"Task 09","description":"Descrição da Task 09","completed_at":null,"created_at":"2023-11-28T11:49:59-03:00","updated_at":"2023-11-28T11:49:59-03:00"},{"id":"14cdae25-a05c-4aa2-b191-52205fac10fd","title":"Task 10","description":"Descrição da Task 10","completed_at":null,"created_at":"2023-11-28T11:49:59-03:00","updated_at":"2023-11-28T11:49:59-03:00"}]}